<?xml version="1.0" encoding="utf-8"?>
<Document>
  <Engineering version="V20" />
  <DocumentInfo>
    <Created>2025-12-01T14:56:27.2462855Z</Created>
    <ExportSetting>None</ExportSetting>
    <InstalledProducts>
      <Product>
        <DisplayName>Totally Integrated Automation Portal</DisplayName>
        <DisplayVersion>V20 Update 3</DisplayVersion>
      </Product>
      <OptionPackage>
        <DisplayName>TIA Portal Openness</DisplayName>
        <DisplayVersion>V20 Update 3</DisplayVersion>
      </OptionPackage>
      <OptionPackage>
        <DisplayName>TIA Portal Version Control Interface</DisplayName>
        <DisplayVersion>V20 Update 3</DisplayVersion>
      </OptionPackage>
      <Product>
        <DisplayName>STEP 7 Professional</DisplayName>
        <DisplayVersion>V20 Update 3</DisplayVersion>
      </Product>
      <OptionPackage>
        <DisplayName>STEP 7 Safety</DisplayName>
        <DisplayVersion>V20 Update 2</DisplayVersion>
      </OptionPackage>
      <Product>
        <DisplayName>WinCC Basic/Comfort/Advanced</DisplayName>
        <DisplayVersion>V20 Update 3</DisplayVersion>
      </Product>
      <Product>
        <DisplayName>WinCC Professional</DisplayName>
        <DisplayVersion>V20 Update 3</DisplayVersion>
      </Product>
      <Product>
        <DisplayName>WinCC Unified</DisplayName>
        <DisplayVersion>V20 Update 3</DisplayVersion>
      </Product>
    </InstalledProducts>
  </DocumentInfo>
  <SW.Blocks.OB ID="0">
    <AttributeList>
      <HeaderAuthor>ESTANDAR</HeaderAuthor>
      <HeaderVersion>3.0</HeaderVersion>
      <Interface><Sections xmlns="http://www.siemens.com/automation/Openness/SW/Interface/v5">
  <Section Name="Temp">
    <Member Name="OB82_EV_CLASS" Datatype="Byte">
      <Comment>
        <MultiLanguageText Lang="es-ES">16#39, Event class 3, Entering event state, Internal fault event</MultiLanguageText>
      </Comment>
    </Member>
    <Member Name="OB82_FLT_ID" Datatype="Byte">
      <Comment>
        <MultiLanguageText Lang="es-ES">16#XX, Fault identifcation code</MultiLanguageText>
      </Comment>
    </Member>
    <Member Name="OB82_PRIORITY" Datatype="Byte">
      <Comment>
        <MultiLanguageText Lang="es-ES">Priority of OB Execution</MultiLanguageText>
      </Comment>
    </Member>
    <Member Name="OB82_OB_NUMBR" Datatype="Byte">
      <Comment>
        <MultiLanguageText Lang="es-ES">82 (Organization block 82, OB82)</MultiLanguageText>
      </Comment>
    </Member>
    <Member Name="OB82_RESERVED_1" Datatype="Byte">
      <Comment>
        <MultiLanguageText Lang="es-ES">Reserved for system</MultiLanguageText>
      </Comment>
    </Member>
    <Member Name="OB82_IO_FLAG" Datatype="Byte">
      <Comment>
        <MultiLanguageText Lang="es-ES">Input (01010100), Output (01010101)</MultiLanguageText>
      </Comment>
    </Member>
    <Member Name="OB82_MDL_ADDR" Datatype="Word">
      <Comment>
        <MultiLanguageText Lang="es-ES">Base address of module with fault</MultiLanguageText>
      </Comment>
    </Member>
    <Member Name="OB82_MDL_DEFECT" Datatype="Bool">
      <Comment>
        <MultiLanguageText Lang="es-ES">Module defective</MultiLanguageText>
      </Comment>
    </Member>
    <Member Name="OB82_INT_FAULT" Datatype="Bool">
      <Comment>
        <MultiLanguageText Lang="es-ES">Internal fault</MultiLanguageText>
      </Comment>
    </Member>
    <Member Name="OB82_EXT_FAULT" Datatype="Bool">
      <Comment>
        <MultiLanguageText Lang="es-ES">External fault</MultiLanguageText>
      </Comment>
    </Member>
    <Member Name="OB82_PNT_INFO" Datatype="Bool">
      <Comment>
        <MultiLanguageText Lang="es-ES">Point information</MultiLanguageText>
      </Comment>
    </Member>
    <Member Name="OB82_EXT_VOLTAGE" Datatype="Bool">
      <Comment>
        <MultiLanguageText Lang="es-ES">External voltage low</MultiLanguageText>
      </Comment>
    </Member>
    <Member Name="OB82_FLD_CONNCTR" Datatype="Bool">
      <Comment>
        <MultiLanguageText Lang="es-ES">Field wiring connector missing</MultiLanguageText>
      </Comment>
    </Member>
    <Member Name="OB82_NO_CONFIG" Datatype="Bool">
      <Comment>
        <MultiLanguageText Lang="es-ES">Module has no configuration data</MultiLanguageText>
      </Comment>
    </Member>
    <Member Name="OB82_CONFIG_ERR" Datatype="Bool">
      <Comment>
        <MultiLanguageText Lang="es-ES">Module has configuration error</MultiLanguageText>
      </Comment>
    </Member>
    <Member Name="OB82_MDL_TYPE" Datatype="Byte">
      <Comment>
        <MultiLanguageText Lang="es-ES">Type of module</MultiLanguageText>
      </Comment>
    </Member>
    <Member Name="OB82_SUB_MDL_ERR" Datatype="Bool">
      <Comment>
        <MultiLanguageText Lang="es-ES">Sub-Module is missing or has error</MultiLanguageText>
      </Comment>
    </Member>
    <Member Name="OB82_COMM_FAULT" Datatype="Bool">
      <Comment>
        <MultiLanguageText Lang="es-ES">Communication fault</MultiLanguageText>
      </Comment>
    </Member>
    <Member Name="OB82_MDL_STOP" Datatype="Bool">
      <Comment>
        <MultiLanguageText Lang="es-ES">Module is stopped</MultiLanguageText>
      </Comment>
    </Member>
    <Member Name="OB82_WTCH_DOG_FLT" Datatype="Bool">
      <Comment>
        <MultiLanguageText Lang="es-ES">Watch dog timer stopped module</MultiLanguageText>
      </Comment>
    </Member>
    <Member Name="OB82_INT_PS_FLT" Datatype="Bool">
      <Comment>
        <MultiLanguageText Lang="es-ES">Internal power supply fault</MultiLanguageText>
      </Comment>
    </Member>
    <Member Name="OB82_PRIM_BATT_FLT" Datatype="Bool">
      <Comment>
        <MultiLanguageText Lang="es-ES">Primary battery is in fault</MultiLanguageText>
      </Comment>
    </Member>
    <Member Name="OB82_BCKUP_BATT_FLT" Datatype="Bool">
      <Comment>
        <MultiLanguageText Lang="es-ES">Backup battery is in fault</MultiLanguageText>
      </Comment>
    </Member>
    <Member Name="OB82_RESERVED_2" Datatype="Bool">
      <Comment>
        <MultiLanguageText Lang="es-ES">Reserved for system</MultiLanguageText>
      </Comment>
    </Member>
    <Member Name="OB82_RACK_FLT" Datatype="Bool">
      <Comment>
        <MultiLanguageText Lang="es-ES">Rack fault, only for bus interface module</MultiLanguageText>
      </Comment>
    </Member>
    <Member Name="OB82_PROC_FLT" Datatype="Bool">
      <Comment>
        <MultiLanguageText Lang="es-ES">Processor fault</MultiLanguageText>
      </Comment>
    </Member>
    <Member Name="OB82_EPROM_FLT" Datatype="Bool">
      <Comment>
        <MultiLanguageText Lang="es-ES">EPROM fault</MultiLanguageText>
      </Comment>
    </Member>
    <Member Name="OB82_RAM_FLT" Datatype="Bool">
      <Comment>
        <MultiLanguageText Lang="es-ES">RAM fault</MultiLanguageText>
      </Comment>
    </Member>
    <Member Name="OB82_ADU_FLT" Datatype="Bool">
      <Comment>
        <MultiLanguageText Lang="es-ES">ADU fault</MultiLanguageText>
      </Comment>
    </Member>
    <Member Name="OB82_FUSE_FLT" Datatype="Bool">
      <Comment>
        <MultiLanguageText Lang="es-ES">Fuse fault</MultiLanguageText>
      </Comment>
    </Member>
    <Member Name="OB82_HW_INTR_FLT" Datatype="Bool">
      <Comment>
        <MultiLanguageText Lang="es-ES">Hardware interupt input in fault</MultiLanguageText>
      </Comment>
    </Member>
    <Member Name="OB82_RESERVED_3" Datatype="Bool">
      <Comment>
        <MultiLanguageText Lang="es-ES">Reserved for system</MultiLanguageText>
      </Comment>
    </Member>
    <Member Name="OB82_DATE_TIME" Datatype="Date_And_Time">
      <Comment>
        <MultiLanguageText Lang="es-ES">Date and time OB82 started</MultiLanguageText>
      </Comment>
    </Member>
  </Section>
  <Section Name="Constant" />
</Sections></Interface>
      <MemoryLayout>Standard</MemoryLayout>
      <Name>OB82_I/O_FLT1</Name>
      <Namespace />
      <Number>82</Number>
      <ProgrammingLanguage>LAD</ProgrammingLanguage>
      <SecondaryType>DiagnosticErrorInterrupt</SecondaryType>
      <SetENOAutomatically>false</SetENOAutomatically>
    </AttributeList>
    <ObjectList>
      <MultilingualText ID="1" CompositionName="Comment">
        <ObjectList>
          <MultilingualTextItem ID="2" CompositionName="Items">
            <AttributeList>
              <Culture>de-DE</Culture>
              <Text />
            </AttributeList>
          </MultilingualTextItem>
          <MultilingualTextItem ID="3" CompositionName="Items">
            <AttributeList>
              <Culture>en-US</Culture>
              <Text />
            </AttributeList>
          </MultilingualTextItem>
          <MultilingualTextItem ID="4" CompositionName="Items">
            <AttributeList>
              <Culture>es-ES</Culture>
              <Text />
            </AttributeList>
          </MultilingualTextItem>
          <MultilingualTextItem ID="5" CompositionName="Items">
            <AttributeList>
              <Culture>fr-FR</Culture>
              <Text />
            </AttributeList>
          </MultilingualTextItem>
          <MultilingualTextItem ID="6" CompositionName="Items">
            <AttributeList>
              <Culture>it-IT</Culture>
              <Text />
            </AttributeList>
          </MultilingualTextItem>
          <MultilingualTextItem ID="7" CompositionName="Items">
            <AttributeList>
              <Culture>ja-JP</Culture>
              <Text />
            </AttributeList>
          </MultilingualTextItem>
          <MultilingualTextItem ID="8" CompositionName="Items">
            <AttributeList>
              <Culture>zh-CN</Culture>
              <Text />
            </AttributeList>
          </MultilingualTextItem>
        </ObjectList>
      </MultilingualText>
      <SW.Blocks.CompileUnit ID="9" CompositionName="CompileUnits">
        <AttributeList>
          <NetworkSource><StatementList xmlns="http://www.siemens.com/automation/Openness/SW/NetworkSource/StatementList/v5" /></NetworkSource>
          <ProgrammingLanguage>STL</ProgrammingLanguage>
        </AttributeList>
        <ObjectList>
          <MultilingualText ID="A" CompositionName="Comment">
            <ObjectList>
              <MultilingualTextItem ID="B" CompositionName="Items">
                <AttributeList>
                  <Culture>de-DE</Culture>
                  <Text />
                </AttributeList>
              </MultilingualTextItem>
              <MultilingualTextItem ID="C" CompositionName="Items">
                <AttributeList>
                  <Culture>en-US</Culture>
                  <Text />
                </AttributeList>
              </MultilingualTextItem>
              <MultilingualTextItem ID="D" CompositionName="Items">
                <AttributeList>
                  <Culture>es-ES</Culture>
                  <Text />
                </AttributeList>
              </MultilingualTextItem>
              <MultilingualTextItem ID="E" CompositionName="Items">
                <AttributeList>
                  <Culture>fr-FR</Culture>
                  <Text />
                </AttributeList>
              </MultilingualTextItem>
              <MultilingualTextItem ID="F" CompositionName="Items">
                <AttributeList>
                  <Culture>it-IT</Culture>
                  <Text />
                </AttributeList>
              </MultilingualTextItem>
              <MultilingualTextItem ID="10" CompositionName="Items">
                <AttributeList>
                  <Culture>ja-JP</Culture>
                  <Text />
                </AttributeList>
              </MultilingualTextItem>
              <MultilingualTextItem ID="11" CompositionName="Items">
                <AttributeList>
                  <Culture>zh-CN</Culture>
                  <Text />
                </AttributeList>
              </MultilingualTextItem>
            </ObjectList>
          </MultilingualText>
          <MultilingualText ID="12" CompositionName="Title">
            <ObjectList>
              <MultilingualTextItem ID="13" CompositionName="Items">
                <AttributeList>
                  <Culture>de-DE</Culture>
                  <Text />
                </AttributeList>
              </MultilingualTextItem>
              <MultilingualTextItem ID="14" CompositionName="Items">
                <AttributeList>
                  <Culture>en-US</Culture>
                  <Text />
                </AttributeList>
              </MultilingualTextItem>
              <MultilingualTextItem ID="15" CompositionName="Items">
                <AttributeList>
                  <Culture>es-ES</Culture>
                  <Text />
                </AttributeList>
              </MultilingualTextItem>
              <MultilingualTextItem ID="16" CompositionName="Items">
                <AttributeList>
                  <Culture>fr-FR</Culture>
                  <Text />
                </AttributeList>
              </MultilingualTextItem>
              <MultilingualTextItem ID="17" CompositionName="Items">
                <AttributeList>
                  <Culture>it-IT</Culture>
                  <Text />
                </AttributeList>
              </MultilingualTextItem>
              <MultilingualTextItem ID="18" CompositionName="Items">
                <AttributeList>
                  <Culture>ja-JP</Culture>
                  <Text />
                </AttributeList>
              </MultilingualTextItem>
              <MultilingualTextItem ID="19" CompositionName="Items">
                <AttributeList>
                  <Culture>zh-CN</Culture>
                  <Text />
                </AttributeList>
              </MultilingualTextItem>
            </ObjectList>
          </MultilingualText>
        </ObjectList>
      </SW.Blocks.CompileUnit>
      <MultilingualText ID="1A" CompositionName="Title">
        <ObjectList>
          <MultilingualTextItem ID="1B" CompositionName="Items">
            <AttributeList>
              <Culture>de-DE</Culture>
              <Text />
            </AttributeList>
          </MultilingualTextItem>
          <MultilingualTextItem ID="1C" CompositionName="Items">
            <AttributeList>
              <Culture>en-US</Culture>
              <Text />
            </AttributeList>
          </MultilingualTextItem>
          <MultilingualTextItem ID="1D" CompositionName="Items">
            <AttributeList>
              <Culture>es-ES</Culture>
              <Text> "I/O Point Fault"</Text>
            </AttributeList>
          </MultilingualTextItem>
          <MultilingualTextItem ID="1E" CompositionName="Items">
            <AttributeList>
              <Culture>fr-FR</Culture>
              <Text />
            </AttributeList>
          </MultilingualTextItem>
          <MultilingualTextItem ID="1F" CompositionName="Items">
            <AttributeList>
              <Culture>it-IT</Culture>
              <Text />
            </AttributeList>
          </MultilingualTextItem>
          <MultilingualTextItem ID="20" CompositionName="Items">
            <AttributeList>
              <Culture>ja-JP</Culture>
              <Text />
            </AttributeList>
          </MultilingualTextItem>
          <MultilingualTextItem ID="21" CompositionName="Items">
            <AttributeList>
              <Culture>zh-CN</Culture>
              <Text />
            </AttributeList>
          </MultilingualTextItem>
        </ObjectList>
      </MultilingualText>
    </ObjectList>
  </SW.Blocks.OB>
</Document>